anonomatic_client/__init__.py
anonomatic_client/client.py
anonomatic_client-0.0.2.dist-info/LICENSE
anonomatic_client-0.0.2.dist-info/METADATA
anonomatic_client-0.0.2.dist-info/WHEEL
anonomatic_client-0.0.2.dist-info/top_level.txt
anonomatic_client-0.0.2.dist-info/RECORD
